{
  "type": "FeatureCollection",
  "features": [
    {
      "type": "Feature",
      "properties": {
        "name": "Ice Fishing Hut"
      },
      "geometry": {
        "type": "Point",
        "coordinates": [
          0.014033317565917969,
          0.0038194656343748757
        ]
      }
    },
    {
      "type": "Feature",
      "properties": {
        "name": "Ice Fishing Hut"
      },
      "geometry": {
        "type": "Point",
        "coordinates": [
          0.0116729736328125,
          0.0026714801778581817
        ]
      }
    },
    {
      "type": "Feature",
      "properties": {
        "name": "Ice Fishing Hut"
      },
      "geometry": {
        "type": "Point",
        "coordinates": [
          0.012488365173339844,
          0.0017380714413795927
        ]
      }
    },
    {
      "type": "Feature",
      "properties": {
        "name": "Ice Fishing Hut"
      },
      "geometry": {
        "type": "Point",
        "coordinates": [
          0.013647079467773438,
          0.0020277500148432005
        ]
      }
    },
    {
      "type": "Feature",
      "properties": {
        "name": "Camp Office"
      },
      "geometry": {
        "type": "Point",
        "coordinates": [
          0.009130239486694336,
          0.003948211666804849
        ]
      }
    },
    {
      "type": "Feature",
      "properties": {
        "name": "Trapper's Homestead"
      },
      "geometry": {
        "type": "Point",
        "coordinates": [
          0.0004076957702636719,
          0.00019311904907751644
        ]
      }
    }
  ]
}
